{
  "name": "TRINCA RV21 - Lead nova para CAPI Lead e WhatsApp Ruria",
  "metadata": {
    "instant": true,
    "version": 1,
    "scenario": {
      "roundtrips": 1,
      "maxErrors": 3,
      "autoCommit": true,
      "autoCommitTriggerLast": true,
      "sequential": false,
      "confidential": false,
      "dataloss": false,
      "dlq": false
    },
    "designer": {
      "orphans": []
    },
    "zone": "us1.make.com",
    "notes": [
      "Importar no Make.com e substituir placeholders de conexao/credenciais.",
      "Cenario D1: lead nova -> Meta CAPI Lead -> notificacao WhatsApp pessoal Ruria.",
      "Se preferir manter credenciais apenas no Vercel, trocar o modulo Meta CAPI por endpoint interno equivalente."
    ]
  },
  "blueprint": {
    "flow": [
      {
        "id": 1,
        "module": "gateway:CustomWebHook",
        "version": 1,
        "parameters": {
          "hook": "__MAKE_WEBHOOK_LEAD__",
          "maxResults": 1
        },
        "mapper": {},
        "metadata": {
          "designer": {
            "x": 0,
            "y": 0
          },
          "restore": {
            "parameters": {
              "hook": {
                "label": "TRINCA RV21 Lead Webhook"
              }
            }
          }
        }
      },
      {
        "id": 2,
        "module": "http:ActionSendData",
        "version": 3,
        "parameters": {
          "handleErrors": true,
          "useNewZLibDeCompress": true
        },
        "mapper": {
          "url": "https://graph.facebook.com/v20.0/__META_PIXEL_ID__/events?access_token=__META_CAPI_ACCESS_TOKEN__",
          "method": "post",
          "headers": [
            {
              "name": "Content-Type",
              "value": "application/json"
            }
          ],
          "bodyType": "raw",
          "contentType": "application/json",
          "data": "{\"data\":[{\"event_name\":\"Lead\",\"event_time\":{{formatDate(now; \"X\")}},\"event_id\":\"lead_{{1.email}}_{{formatDate(now; \"X\")}}\",\"action_source\":\"website\",\"event_source_url\":\"https://protocolorv.com.br/\",\"user_data\":{\"em\":\"{{sha256(lower(1.email))}}\",\"ph\":\"{{sha256(replace(1.whatsapp; \"/\\D/g\"; \"\"))}}\"},\"custom_data\":{\"content_name\":\"TRINCA RV21\",\"lead_source\":\"{{ifempty(1.origem; \"make-webhook-lead\")}}\",\"objective\":\"{{1.objetivo}}\"}}]}"
        },
        "metadata": {
          "designer": {
            "x": 300,
            "y": 0
          }
        }
      },
      {
        "id": 3,
        "module": "http:ActionSendData",
        "version": 3,
        "parameters": {
          "handleErrors": true,
          "useNewZLibDeCompress": true
        },
        "mapper": {
          "url": "https://protocolorv.com.br/api/leads",
          "method": "post",
          "headers": [
            {
              "name": "Content-Type",
              "value": "application/json"
            }
          ],
          "bodyType": "raw",
          "contentType": "application/json",
          "data": "{\"nome\":\"{{1.nome}}\",\"email\":\"{{1.email}}\",\"whatsapp\":\"{{1.whatsapp}}\",\"objetivo\":\"{{1.objetivo}}\",\"origem\":\"{{ifempty(1.origem; \"make-webhook-lead\")}}\",\"status\":\"novo-lead\",\"etapaFunil\":\"captacao\",\"utm\":\"{{ifempty(1.utm; 1.utm_source)}}\",\"checkoutUrl\":\"{{ifempty(1.checkoutUrl; \"https://pay.kiwify.com.br/mEhmYNt\")}}\",\"data\":\"{{now}}\"}"
        },
        "metadata": {
          "designer": {
            "x": 600,
            "y": 0
          }
        }
      },
      {
        "id": 4,
        "module": "http:ActionSendData",
        "version": 3,
        "parameters": {
          "handleErrors": true,
          "useNewZLibDeCompress": true
        },
        "mapper": {
          "url": "https://api.twilio.com/2010-04-01/Accounts/__TWILIO_ACCOUNT_SID__/Messages.json",
          "method": "post",
          "headers": [
            {
              "name": "Authorization",
              "value": "Basic __TWILIO_BASIC_AUTH_BASE64__"
            },
            {
              "name": "Content-Type",
              "value": "application/x-www-form-urlencoded"
            }
          ],
          "bodyType": "raw",
          "contentType": "application/x-www-form-urlencoded",
          "data": "To=whatsapp%3A%2B5584998567078&From=whatsapp%3A%2B__TWILIO_WHATSAPP_FROM__&Body=Novo%20lead%20TRINCA%20RV21%3A%20{{1.nome}}%20-%20{{1.whatsapp}}%20-%20{{1.objetivo}}"
        },
        "metadata": {
          "designer": {
            "x": 900,
            "y": 0
          }
        }
      }
    ]
  }
}
